dcc_notification/__init__.py
dcc_notification/manager.py
dcc_notification/notification_message.py
dcc_notification/notification_wrapper.py
dcc_notifications-0.0.2.dist-info/LICENSE
dcc_notifications-0.0.2.dist-info/METADATA
dcc_notifications-0.0.2.dist-info/WHEEL
dcc_notifications-0.0.2.dist-info/top_level.txt
dcc_notifications-0.0.2.dist-info/RECORD
