Metadata-Version: 2.1
Name: dcc-notifications
Version: 0.0.2
Summary: Experimental library for showing notifications in DCC applications
Author: Nils Soderman
License: MIT No Attribution
Project-URL: Homepage, https://github.com/nils-soderman/dcc-notifications
Project-URL: Bug Tracker, https://github.com/nils-soderman/dcc-notifications/issues
Classifier: Programming Language :: Python :: 3
Classifier: License :: OSI Approved :: MIT No Attribution License (MIT-0)
Classifier: Operating System :: OS Independent
Classifier: Development Status :: 2 - Pre-Alpha
Requires-Python: >=3.7
License-File: LICENSE
